{
  "name": "geoform",
  "image": "mcr.microsoft.com/devcontainers/base:debian",
  "features": {
    "ghcr.io/devcontainers/features/node:1": {
      "version": "25"
    },
    "ghcr.io/devcontainers-community/features/deno:1": {
      "version": "2.6.5"
    },
    "ghcr.io/dhoeric/features/hadolint:1": {}
  },
  "forwardPorts": [
    5173
  ],
  "portsAttributes": {
    "5173": {
      "label": "Vite app"
    }
  },
  "workspaceFolder": "/workspaces/${localWorkspaceFolderBasename}",
  "runArgs": [
    "--init",
    "--network",
    "shared-net"
  ],
  "containerEnv": {
    "NODE_ENV": "development",
    "CHOKIDAR_USEPOLLING": "true",
    "COREPACK_ENABLE_STRICT": "0",
    "TMPDIR": "/tmp",
    "PNPM_HOME": "/home/vscode/.local/share/pnpm/store"
  },
  "mounts": [
    "source=${localWorkspaceFolderBasename}-node_modules,target=${containerWorkspaceFolder}/node_modules,type=volume"
  ],
  "postAttachCommand": "sudo chown vscode:vscode node_modules && pnpm install --frozen-lockfile && pnpm run prepare && pnpm dev",
  "remoteUser": "vscode",
  "customizations": {
    "vscode": {
      "extensions": [
        "denoland.vscode-deno",
        "exiasr.hadolint"
      ],
      "settings": {
        "editor.formatOnSave": true
      }
    }
  }
}
